{"paragraphs":[{"text":"\nimport org.apache.spark.sql.types._\nimport org.apache.spark.sql.functions._\nimport org.apache.spark.sql._\nimport org.apache.spark.streaming._\n\nimport org.apache.spark.ml.feature.VectorAssembler\nimport org.apache.spark.ml.clustering.KMeansModel\n","user":"mapr","dateUpdated":"2018-10-30T16:14:36+0000","config":{"tableHide":false,"editorSetting":{"language":"scala","editOnDblClick":false,"completionKey":"TAB","completionSupport":true},"colWidth":12,"editorMode":"ace/mode/scala","editorHide":false,"results":{},"enabled":true,"fontSize":9},"settings":{"params":{},"forms":{}},"results":{"code":"SUCCESS","msg":[{"type":"TEXT","data":"import org.apache.spark.sql.types._\nimport org.apache.spark.sql.functions._\nimport org.apache.spark.sql._\nimport org.apache.spark.streaming._\nimport org.apache.spark.ml.feature.VectorAssembler\nimport org.apache.spark.ml.clustering.KMeansModel\n"}]},"apps":[],"jobName":"paragraph_1540326162159_-1205153931","id":"20170919-164412_663650782","dateCreated":"2018-10-23T20:22:42+0000","dateStarted":"2018-10-30T16:14:36+0000","dateFinished":"2018-10-30T16:14:38+0000","status":"FINISHED","progressUpdateIntervalMs":500,"focus":true,"$$hashKey":"object:23080"},{"title":"Load the saved Machine Learning model ","text":"val model = KMeansModel.load(\"/user/mapr/ubermodel\")\n// Create a dataframe with cluster id and location\ncase class Center(cid: Integer, clat: Double, clon: Double)   extends Serializable \nvar ac = new Array[Center](20)\nvar index: Int = 0\n model.clusterCenters.foreach(x => {\n      ac(index) = Center(index, x(0), x(1));\n      index += 1;\n    })\n val ccdf = spark.createDataset(ac)\n ccdf.show ","user":"mapr","dateUpdated":"2018-10-29T20:43:07+0000","config":{"editorSetting":{"language":"scala","editOnDblClick":false,"completionKey":"TAB","completionSupport":true},"colWidth":12,"editorMode":"ace/mode/scala","title":true,"results":{},"enabled":true,"fontSize":9,"editorHide":false},"settings":{"params":{},"forms":{}},"results":{"code":"SUCCESS","msg":[{"type":"TEXT","data":"model: org.apache.spark.ml.clustering.KMeansModel = kmeans_4ad427355253\ndefined class Center\nac: Array[Center] = Array(null, null, null, null, null, null, null, null, null, null, null, null, null, null, null, null, null, null, null, null)\nindex: Int = 0\nccdf: org.apache.spark.sql.Dataset[Center] = [cid: int, clat: double ... 1 more field]\n+---+------------------+------------------+\n|cid|              clat|              clon|\n+---+------------------+------------------+\n|  0|40.718921849974365|-74.00490159401888|\n|  1|  40.8610796301731|-73.90554857646023|\n|  2| 40.76039386666665|-73.46966613333332|\n|  3|40.759424009301696|-73.86168843135333|\n|  4| 40.62595994615613|-73.97991474723302|\n|  5|40.760445904971284|-73.98056761384093|\n|  6| 40.73831444313262|-73.99307166127669|\n|  7|40.687537560478695| -73.9296368220016|\n|  8| 40.17341304347826|-74.04630559006209|\n|  9| 41.00501994301994|-73.76936239316241|\n| 10| 40.64975699907317|-73.78446796450795|\n| 11|40.802719736199194|-73.95815917928675|\n| 12|40.745914507772014|-73.66162357512955|\n| 13| 40.68250103990326|-73.98149835550159|\n| 14|40.660174766355134|-74.39607476635511|\n| 15|40.799158585858585|-73.09681717171716|\n| 16| 40.76948423304467|-73.94946381259255|\n| 17|40.718272100336435|-73.95378002047677|\n| 18| 40.69810819672119|-74.18120871440901|\n| 19| 40.92297466666666|-74.11527413333333|\n+---+------------------+------------------+\n\n"}]},"runtimeInfos":{"jobUrl":{"propertyName":"jobUrl","label":"SPARK JOB","tooltip":"View in Spark web UI","group":"spark","values":["http://mapr-resman:8088/proxy/application_1540577802860_0022//jobs","http://mapr-resman:8088/proxy/application_1540577802860_0022//jobs","http://mapr-resman:8088/proxy/application_1540577802860_0022//jobs"],"interpreterSettingId":"spark"}},"apps":[],"jobName":"paragraph_1540326162161_1612252360","id":"20180703-075217_1487726440","dateCreated":"2018-10-23T20:22:42+0000","dateStarted":"2018-10-29T20:43:07+0000","dateFinished":"2018-10-29T20:43:10+0000","status":"FINISHED","progressUpdateIntervalMs":500,"$$hashKey":"object:23081"},{"title":"Define the Uber Schema","text":"case class Uber(dt: String, lat: Double, lon: Double, base: String, rdt: String)   extends Serializable\n // Parse string into Uber case class\n def parseUber(str: String): Uber = {\n    val p = str.split(\",\")\n    Uber(p(0), p(1).toDouble, p(2).toDouble, p(3), p(4))\n }  ","user":"mapr","dateUpdated":"2018-10-30T17:34:25+0000","config":{"editorSetting":{"language":"scala","editOnDblClick":false,"completionKey":"TAB","completionSupport":true},"colWidth":12,"editorMode":"ace/mode/scala","editorHide":false,"title":true,"results":{},"enabled":true,"fontSize":9},"settings":{"params":{},"forms":{}},"results":{"code":"SUCCESS","msg":[{"type":"TEXT","data":"defined class Uber\nparseUber: (str: String)Uber\n"}]},"apps":[],"jobName":"paragraph_1540326162162_1200408415","id":"20180614-162851_1497489065","dateCreated":"2018-10-23T20:22:42+0000","dateStarted":"2018-10-29T20:43:15+0000","dateFinished":"2018-10-29T20:43:16+0000","status":"FINISHED","progressUpdateIntervalMs":500,"$$hashKey":"object:23082"},{"title":"Read the data from a topic into a Dataframe","text":"\nvar topic: String = \"/user/mapr/uberstream:ubers\"\n\nval df1 = spark.readStream.format(\"kafka\").option(\"kafka.bootstrap.servers\", \"maprdemo:9092\" ).option(\"subscribe\", topic).option(\"group.id\", \"testgroup\").option(\"startingOffsets\", \"earliest\").option(\"failOnDataLoss\", false).option(\"maxOffsetsPerTrigger\", 100).load()\n\nimport spark.implicits._\n\nspark.udf.register(\"deserialize\", (message: String) => parseUber(message))\n\nval df2 = df1.selectExpr(\"\"\"deserialize(CAST(value as STRING)) AS message\"\"\").select($\"message\".as[Uber])     \n\n","user":"mapr","dateUpdated":"2018-10-29T20:43:23+0000","config":{"tableHide":false,"editorSetting":{"language":"scala","editOnDblClick":false,"completionKey":"TAB","completionSupport":true},"colWidth":12,"editorMode":"ace/mode/scala","editorHide":false,"title":true,"results":{},"enabled":true,"fontSize":9},"settings":{"params":{},"forms":{}},"results":{"code":"SUCCESS","msg":[{"type":"TEXT","data":"topic: String = /user/mapr/uberstream:ubers\ndf1: org.apache.spark.sql.DataFrame = [key: binary, value: binary ... 5 more fields]\nimport spark.implicits._\nres35: org.apache.spark.sql.expressions.UserDefinedFunction = UserDefinedFunction(<function1>,StructType(StructField(dt,StringType,true), StructField(lat,DoubleType,false), StructField(lon,DoubleType,false), StructField(base,StringType,true), StructField(rdt,StringType,true)),Some(List(StringType)))\ndf2: org.apache.spark.sql.Dataset[Uber] = [dt: string, lat: double ... 3 more fields]\n"}]},"apps":[],"jobName":"paragraph_1540326162163_217618825","id":"20170912-093030_1095767690","dateCreated":"2018-10-23T20:22:42+0000","dateStarted":"2018-10-29T20:43:23+0000","dateFinished":"2018-10-29T20:43:26+0000","status":"FINISHED","progressUpdateIntervalMs":500,"$$hashKey":"object:23083"},{"title":"Print the Kafka DataFrame schema","text":"df1.printSchema()","user":"mapr","dateUpdated":"2018-10-29T20:48:40+0000","config":{"tableHide":false,"editorSetting":{"language":"scala","editOnDblClick":false,"completionKey":"TAB","completionSupport":true},"colWidth":12,"editorMode":"ace/mode/scala","editorHide":false,"results":{"0":{"graph":{"mode":"table","height":626,"optionOpen":false}}},"enabled":true,"fontSize":9,"title":true},"settings":{"params":{},"forms":{}},"results":{"code":"SUCCESS","msg":[{"type":"TEXT","data":"root\n |-- key: binary (nullable = true)\n |-- value: binary (nullable = true)\n |-- topic: string (nullable = true)\n |-- partition: integer (nullable = true)\n |-- offset: long (nullable = true)\n |-- timestamp: timestamp (nullable = true)\n |-- timestampType: integer (nullable = true)\n\n"}]},"apps":[],"jobName":"paragraph_1540326162164_397194052","id":"20170918-213807_1223642162","dateCreated":"2018-10-23T20:22:42+0000","dateStarted":"2018-10-29T20:43:34+0000","dateFinished":"2018-10-29T20:43:34+0000","status":"FINISHED","progressUpdateIntervalMs":500,"$$hashKey":"object:23084"},{"title":"Add the Cluster Id for trip location from Model to a Dataframe","text":"\nval featureCols = Array(\"lat\", \"lon\")\nval assembler = new VectorAssembler().setInputCols(featureCols).setOutputCol(\"features\")\nval df3 = assembler.transform(df2)\n\nval clusters1 = model.transform(df3)\n\nval temp= clusters1.select($\"dt\".cast(TimestampType),  $\"lat\", $\"lon\", $\"base\",$\"rdt\", $\"cid\")\n    \n // Uber class enriched with Cluster id and  cluster lat lon\ncase class UberC(dt: java.sql.Timestamp, lat: Double, lon: Double, base: String, rdt: String, cid: Integer, clat: Double, clon: Double) extends Serializable\n\nval clusters = temp.join(ccdf, Seq(\"cid\")).as[UberC]\n\n      \n     ","user":"mapr","dateUpdated":"2018-10-29T20:43:40+0000","config":{"editorSetting":{"language":"scala","editOnDblClick":false,"completionKey":"TAB","completionSupport":true},"colWidth":12,"editorMode":"ace/mode/scala","editorHide":false,"title":true,"results":{},"enabled":true,"fontSize":9},"settings":{"params":{},"forms":{}},"results":{"code":"SUCCESS","msg":[{"type":"TEXT","data":"featureCols: Array[String] = Array(lat, lon)\nassembler: org.apache.spark.ml.feature.VectorAssembler = vecAssembler_616d6c3aed49\ndf3: org.apache.spark.sql.DataFrame = [dt: string, lat: double ... 4 more fields]\nclusters1: org.apache.spark.sql.DataFrame = [dt: string, lat: double ... 5 more fields]\ntemp: org.apache.spark.sql.DataFrame = [dt: timestamp, lat: double ... 4 more fields]\ndefined class UberC\nclusters: org.apache.spark.sql.Dataset[UberC] = [cid: int, dt: timestamp ... 6 more fields]\n"}]},"apps":[],"jobName":"paragraph_1540326162165_814083783","id":"20180614-163504_856983168","dateCreated":"2018-10-23T20:22:42+0000","dateStarted":"2018-10-29T20:43:40+0000","dateFinished":"2018-10-29T20:43:43+0000","status":"FINISHED","progressUpdateIntervalMs":500,"$$hashKey":"object:23085"},{"title":"Create column with unique Id in order to write to MapR-DB","text":"// Uber with unique Id and Cluster id and  cluster lat lon\ncase class UberwId(_id: String, dt: java.sql.Timestamp, lat: Double, lon: Double,  \n    base: String, cid: Integer, clat: Double, clon: Double) extends Serializable\n    \nval cdf = clusters.withColumn(\"_id\", concat($\"cid\", lit(\"_\"), $\"rdt\")).as[UberwId]\n     \n","user":"mapr","dateUpdated":"2018-10-29T20:49:23+0000","config":{"colWidth":12,"editorMode":"ace/mode/scala","results":{},"enabled":true,"editorSetting":{"language":"scala","editOnDblClick":false,"completionKey":"TAB","completionSupport":true},"fontSize":9,"editorHide":false,"title":true},"settings":{"params":{},"forms":{}},"results":{"code":"SUCCESS","msg":[{"type":"TEXT","data":"defined class UberwId\ncreateUberwId: (uber: UberC)UberwId\ncdf: org.apache.spark.sql.Dataset[UberwId] = [cid: int, dt: timestamp ... 7 more fields]\n"}]},"apps":[],"jobName":"paragraph_1540326162166_-621483238","id":"20180709-161013_1427000981","dateCreated":"2018-10-23T20:22:42+0000","dateStarted":"2018-10-29T20:44:37+0000","dateFinished":"2018-10-29T20:44:38+0000","status":"FINISHED","progressUpdateIntervalMs":500,"$$hashKey":"object:23086"},{"title":"Write Stream to Memory for Display Purposes","text":"val streamingquery = cdf.writeStream.queryName(\"uber\").format(\"memory\").outputMode(\"append\").start","user":"mapr","dateUpdated":"2018-10-29T20:50:21+0000","config":{"colWidth":12,"editorMode":"ace/mode/scala","results":{},"enabled":true,"editorSetting":{"language":"scala","editOnDblClick":false,"completionKey":"TAB","completionSupport":true},"fontSize":9,"editorHide":false,"title":true},"settings":{"params":{},"forms":{}},"results":{"code":"SUCCESS","msg":[{"type":"TEXT","data":"streamingquery: org.apache.spark.sql.streaming.StreamingQuery = org.apache.spark.sql.execution.streaming.StreamingQueryWrapper@6dfb9ee6\n"}]},"apps":[],"jobName":"paragraph_1540326162167_-2056500087","id":"20180702-164624_781461375","dateCreated":"2018-10-23T20:22:42+0000","dateStarted":"2018-10-29T20:44:44+0000","dateFinished":"2018-10-29T20:44:45+0000","status":"FINISHED","progressUpdateIntervalMs":500,"$$hashKey":"object:23087"},{"title":"Query Streaming Memory output","text":"%sql  select * from uber limit 10","user":"mapr","dateUpdated":"2018-10-29T20:50:42+0000","config":{"colWidth":12,"editorMode":"ace/mode/sql","results":{"0":{"graph":{"mode":"table","height":300,"optionOpen":false,"setting":{"table":{"tableGridState":{},"tableColumnTypeState":{"names":{"cid":"string","dt":"string","lat":"string","lon":"string","base":"string","rdt":"string","clat":"string","clon":"string","_id":"string"},"updated":false},"tableOptionSpecHash":"[{\"name\":\"useFilter\",\"valueType\":\"boolean\",\"defaultValue\":false,\"widget\":\"checkbox\",\"description\":\"Enable filter for columns\"},{\"name\":\"showPagination\",\"valueType\":\"boolean\",\"defaultValue\":false,\"widget\":\"checkbox\",\"description\":\"Enable pagination for better navigation\"},{\"name\":\"showAggregationFooter\",\"valueType\":\"boolean\",\"defaultValue\":false,\"widget\":\"checkbox\",\"description\":\"Enable a footer for displaying aggregated values\"}]","tableOptionValue":{"useFilter":false,"showPagination":false,"showAggregationFooter":false},"updated":false,"initialized":false}},"commonSetting":{}}}},"enabled":true,"editorSetting":{"language":"sql","editOnDblClick":false,"completionKey":"TAB","completionSupport":true},"fontSize":9,"editorHide":false,"title":true},"settings":{"params":{},"forms":{}},"results":{"code":"SUCCESS","msg":[{"type":"TABLE","data":"cid\tdt\tlat\tlon\tbase\trdt\tclat\tclon\t_id\n6\t2014-08-01 00:00:00.0\t40.7406\t-73.9902\tB02598\t9223370496455090720\t40.73831444313262\t-73.99307166127669\t6_9223370496455090720\n13\t2014-08-01 00:00:00.0\t40.6759\t-74.0168\tB02617\t9223370496455090479\t40.68250103990326\t-73.98149835550159\t13_9223370496455090479\n13\t2014-08-01 00:00:00.0\t40.6982\t-73.9669\tB02617\t9223370496455090238\t40.68250103990326\t-73.98149835550159\t13_9223370496455090238\n0\t2014-08-01 00:00:00.0\t40.7303\t-74.0029\tB02682\t9223370496455089997\t40.718921849974365\t-74.00490159401888\t0_9223370496455089997\n5\t2014-08-01 00:00:00.0\t40.762\t-73.983\tB02682\t9223370496455089756\t40.760445904971284\t-73.98056761384093\t5_9223370496455089756\n5\t2014-08-01 00:00:00.0\t40.751\t-73.9869\tB02598\t9223370496455090780\t40.760445904971284\t-73.98056761384093\t5_9223370496455090780\n7\t2014-08-01 00:00:00.0\t40.7063\t-73.9223\tB02617\t9223370496455090540\t40.687537560478695\t-73.9296368220016\t7_9223370496455090540\n5\t2014-08-01 00:00:00.0\t40.7623\t-73.9751\tB02617\t9223370496455090298\t40.760445904971284\t-73.98056761384093\t5_9223370496455090298\n13\t2014-08-01 00:00:00.0\t40.6754\t-74.017\tB02682\t9223370496455090057\t40.68250103990326\t-73.98149835550159\t13_9223370496455090057\n0\t2014-08-01 00:00:00.0\t40.7194\t-73.9964\tB02682\t9223370496455089816\t40.718921849974365\t-74.00490159401888\t0_9223370496455089816\n"}]},"runtimeInfos":{"jobUrl":{"propertyName":"jobUrl","label":"SPARK JOB","tooltip":"View in Spark web UI","group":"spark","values":["http://mapr-resman:8088/proxy/application_1540577802860_0022//jobs"],"interpreterSettingId":"spark"}},"apps":[],"jobName":"paragraph_1540326162167_-867471831","id":"20180703-124444_301447550","dateCreated":"2018-10-23T20:22:42+0000","dateStarted":"2018-10-29T20:44:49+0000","dateFinished":"2018-10-29T20:44:49+0000","status":"FINISHED","progressUpdateIntervalMs":500,"$$hashKey":"object:23088"},{"title":"What is the trip count by hour and cluster?","text":"%sql\nSELECT hour(uber.dt) as hr,cid, count(cid) as ct FROM uber group By hour(uber.dt), cid","user":"mapr","dateUpdated":"2018-10-30T16:14:16+0000","config":{"colWidth":12,"editorMode":"ace/mode/sql","results":{"0":{"graph":{"mode":"multiBarChart","height":300,"optionOpen":false,"setting":{"multiBarChart":{"rotate":{"degree":"-45"},"xLabelStatus":"default","stacked":true}},"commonSetting":{},"keys":[{"name":"hr","index":0,"aggr":"sum"}],"groups":[{"name":"cid","index":1,"aggr":"sum"}],"values":[{"name":"ct","index":2,"aggr":"sum"}]},"helium":{}}},"enabled":true,"editorSetting":{"language":"sql","editOnDblClick":false,"completionKey":"TAB","completionSupport":true},"fontSize":9,"editorHide":false,"title":true},"settings":{"params":{},"forms":{}},"results":{"code":"SUCCESS","msg":[{"type":"TABLE","data":"hr\tcid\tct\n15\t14\t1\n10\t2\t8\n23\t6\t1033\n16\t3\t195\n17\t2\t11\n17\t1\t59\n13\t10\t128\n9\t10\t40\n9\t16\t242\n1\t0\t549\n4\t10\t52\n5\t16\t126\n6\t1\t21\n3\t1\t18\n17\t3\t169\n7\t4\t29\n22\t8\t14\n12\t19\t2\n18\t16\t456\n22\t9\t10\n2\t2\t2\n18\t1\t42\n22\t6\t1281\n9\t4\t39\n8\t9\t4\n12\t7\t120\n8\t3\t77\n19\t2\t7\n10\t15\t2\n0\t13\t256\n3\t13\t84\n7\t14\t2\n2\t19\t5\n12\t17\t160\n20\t2\t5\n3\t18\t1\n1\t7\t102\n11\t8\t1\n23\t17\t314\n11\t6\t672\n2\t3\t25\n4\t7\t60\n7\t1\t32\n14\t16\t280\n12\t2\t7\n15\t12\t15\n6\t17\t114\n14\t14\t12\n9\t13\t211\n21\t11\t154\n0\t14\t4\n1\t2\t2\n16\t2\t6\n13\t7\t119\n20\t12\t11\n0\t7\t150\n11\t1\t45\n18\t14\t3\n9\t1\t31\n19\t13\t324\n6\t0\t236\n14\t11\t160\n16\t15\t1\n17\t19\t6\n23\t0\t677\n13\t15\t1\n10\t13\t225\n10\t18\t19\n14\t15\t2\n17\t7\t134\n16\t8\t2\n23\t16\t174\n4\t0\t173\n1\t9\t5\n13\t9\t6\n15\t1\t65\n21\t16\t252\n10\t16\t291\n0\t5\t469\n16\t16\t409\n22\t19\t7\n23\t2\t5\n5\t7\t83\n15\t5\t1223\n23\t12\t17\n5\t6\t273\n4\t11\t64\n12\t1\t52\n8\t13\t162\n16\t0\t836\n11\t16\t280\n15\t6\t1164\n19\t19\t6\n20\t14\t4\n14\t3\t181\n17\t10\t156\n6\t8\t1\n10\t5\t668\n16\t4\t54\n14\t13\t316\n17\t14\t5\n1\t1\t29\n8\t14\t2\n9\t7\t104\n4\t9\t3\n6\t5\t302\n17\t18\t51\n1\t3\t28\n2\t17\t151\n6\t13\t134\n6\t12\t2\n20\t15\t1\n20\t3\t204\n8\t12\t12\n11\t4\t52\n10\t6\t620\n18\t9\t17\n19\t1\t53\n3\t10\t11\n6\t18\t14\n2\t14\t1\n11\t7\t119\n21\t5\t868\n3\t5\t258\n7\t19\t4\n13\t5\t792\n20\t11\t167\n15\t2\t4\n19\t17\t286\n1\t11\t65\n2\t5\t230\n15\t11\t166\n21\t6\t967\n0\t16\t154\n23\t19\t4\n15\t8\t1\n0\t0\t681\n17\t6\t1304\n7\t2\t3\n15\t10\t153\n16\t9\t12\n1\t4\t28\n14\t2\t6\n18\t8\t3\n21\t10\t87\n5\t4\t20\n5\t17\t80\n0\t10\t53\n12\t5\t758\n9\t12\t9\n17\t13\t393\n7\t9\t5\n18\t10\t117\n21\t3\t155\n23\t3\t69\n11\t19\t7\n5\t12\t4\n0\t17\t334\n2\t9\t6\n4\t17\t90\n14\t4\t66\n21\t2\t7\n10\t4\t49\n4\t13\t55\n5\t13\t94\n8\t10\t38\n10\t1\t48\n11\t5\t715\n19\t4\t75\n7\t3\t63\n8\t19\t5\n2\t15\t1\n3\t3\t14\n15\t7\t103\n22\t11\t128\n23\t5\t568\n9\t3\t133\n17\t11\t204\n22\t14\t6\n1\t8\t2\n21\t4\t50\n9\t2\t4\n16\t17\t246\n21\t14\t9\n16\t7\t119\n21\t12\t25\n3\t17\t104\n17\t8\t4\n1\t16\t97\n8\t5\t549\n22\t18\t21\n1\t19\t7\n11\t9\t8\n22\t17\t277\n8\t1\t40\n12\t15\t2\n17\t9\t15\n13\t4\t68\n0\t9\t10\n21\t7\t109\n3\t19\t2\n21\t19\t9\n22\t0\t797\n4\t3\t24\n6\t7\t90\n15\t17\t241\n7\t12\t7\n2\t1\t19\n14\t6\t911\n8\t11\t144\n15\t18\t40\n18\t6\t1238\n10\t19\t4\n2\t18\t4\n7\t11\t139\n8\t18\t18\n20\t13\t312\n14\t19\t6\n15\t9\t13\n13\t18\t44\n7\t16\t268\n2\t4\t24\n3\t11\t56\n14\t0\t687\n20\t18\t30\n23\t18\t20\n22\t15\t4\n11\t3\t136\n18\t5\t1266\n12\t14\t4\n0\t15\t2\n9\t11\t134\n18\t15\t2\n19\t14\t4\n20\t5\t812\n21\t0\t655\n21\t8\t9\n4\t6\t262\n6\t3\t38\n16\t18\t63\n12\t0\t460\n3\t14\t1\n13\t3\t160\n21\t13\t281\n19\t6\t1147\n7\t17\t155\n18\t11\t201\n8\t17\t139\n0\t18\t16\n1\t18\t15\n8\t7\t77\n12\t12\t10\n11\t13\t214\n12\t8\t1\n7\t18\t15\n17\t12\t21\n3\t6\t504\n13\t11\t164\n8\t2\t5\n7\t5\t484\n5\t10\t103\n13\t6\t806\n13\t16\t286\n11\t18\t34\n22\t16\t233\n1\t14\t3\n16\t1\t53\n6\t2\t1\n9\t5\t584\n16\t6\t1248\n0\t11\t104\n3\t9\t2\n10\t9\t9\n20\t8\t5\n22\t10\t90\n23\t7\t148\n16\t11\t180\n18\t0\t845\n12\t4\t46\n15\t13\t301\n19\t7\t130\n23\t14\t3\n0\t1\t38\n2\t0\t325\n11\t0\t467\n11\t11\t153\n17\t4\t73\n21\t1\t39\n0\t19\t10\n11\t14\t2\n1\t17\t202\n16\t14\t2\n18\t18\t39\n18\t2\t16\n19\t18\t40\n21\t17\t264\n14\t9\t10\n5\t18\t21\n19\t16\t385\n20\t0\t664\n11\t17\t167\n20\t7\t138\n4\t19\t2\n18\t4\t48\n20\t1\t48\n6\t10\t68\n18\t17\t295\n13\t0\t518\n12\t9\t12\n17\t17\t272\n23\t8\t8\n2\t11\t54\n2\t12\t5\n16\t19\t7\n20\t10\t114\n22\t7\t130\n23\t9\t11\n2\t10\t15\n8\t4\t44\n18\t7\t136\n8\t15\t1\n13\t2\t6\n21\t18\t23\n7\t13\t158\n1\t12\t10\n23\t11\t100\n10\t3\t132\n18\t13\t391\n15\t4\t64\n5\t0\t188\n19\t12\t13\n22\t13\t301\n0\t8\t12\n3\t2\t1\n1\t5\t355\n23\t13\t283\n5\t2\t1\n13\t14\t5\n15\t3\t191\n20\t16\t297\n20\t9\t8\n11\t15\t3\n12\t18\t31\n10\t12\t13\n14\t7\t132\n5\t1\t17\n8\t0\t372\n9\t0\t352\n5\t3\t33\n16\t10\t142\n19\t9\t9\n6\t11\t97\n9\t18\t11\n1\t15\t3\n20\t4\t47\n14\t18\t28\n23\t4\t35\n9\t14\t4\n19\t3\t206\n0\t6\t1209\n12\t6\t709\n9\t9\t10\n14\t12\t13\n18\t3\t186\n0\t2\t5\n3\t12\t3\n7\t7\t74\n1\t13\t129\n10\t11\t152\n23\t1\t41\n10\t17\t163\n17\t15\t4\n19\t5\t987\n3\t4\t19\n4\t18\t13\n7\t10\t63\n6\t16\t191\n19\t15\t1\n14\t1\t42\n22\t5\t799\n13\t12\t17\n4\t4\t23\n12\t11\t130\n10\t10\t42\n11\t2\t3\n17\t5\t1278\n21\t9\t10\n10\t14\t2\n12\t13\t248\n6\t6\t378\n8\t6\t623\n15\t19\t3\n10\t7\t109\n0\t3\t45\n3\t16\t94\n13\t17\t212\n20\t17\t222\n12\t10\t78\n20\t6\t957\n3\t0\t174\n12\t16\t283\n13\t19\t1\n9\t6\t594\n10\t0\t421\n1\t6\t903\n14\t5\t972\n1\t10\t22\n4\t1\t15\n3\t7\t68\n13\t1\t49\n6\t9\t3\n9\t19\t2\n19\t0\t790\n0\t4\t36\n13\t13\t270\n16\t5\t1433\n5\t9\t4\n18\t19\t2\n20\t19\t2\n5\t11\t75\n15\t16\t353\n17\t16\t412\n18\t12\t13\n19\t8\t3\n2\t7\t78\n4\t16\t91\n12\t3\t135\n19\t10\t169\n22\t2\t11\n9\t17\t178\n11\t12\t18\n17\t0\t942\n22\t12\t16\n23\t10\t62\n0\t12\t16\n4\t5\t201\n22\t4\t53\n14\t10\t177\n16\t13\t376\n14\t17\t220\n15\t0\t793\n5\t5\t231\n8\t16\t300\n7\t0\t310\n7\t6\t517\n16\t12\t13\n19\t11\t192\n2\t13\t83\n2\t16\t66\n11\t10\t54\n22\t1\t52\n22\t3\t113\n4\t12\t6\n6\t4\t25\n10\t8\t1\n2\t6\t576\n"}]},"runtimeInfos":{"jobUrl":{"propertyName":"jobUrl","label":"SPARK JOB","tooltip":"View in Spark web UI","group":"spark","values":["http://mapr-resman:8088/proxy/application_1540577802860_0022//jobs","http://mapr-resman:8088/proxy/application_1540577802860_0022//jobs","http://mapr-resman:8088/proxy/application_1540577802860_0022//jobs","http://mapr-resman:8088/proxy/application_1540577802860_0022//jobs","http://mapr-resman:8088/proxy/application_1540577802860_0022//jobs"],"interpreterSettingId":"spark"}},"apps":[],"jobName":"paragraph_1540326162168_1818060191","id":"20180711-162209_475986403","dateCreated":"2018-10-23T20:22:42+0000","dateStarted":"2018-10-29T20:46:30+0000","dateFinished":"2018-10-29T20:46:31+0000","status":"FINISHED","progressUpdateIntervalMs":500,"$$hashKey":"object:23089"},{"title":"What is the trip Count by Cluster?","text":"%sql  select cid, count(cid) as count from uber group by cid","user":"mapr","dateUpdated":"2018-10-30T16:14:16+0000","config":{"colWidth":12,"editorMode":"ace/mode/sql","results":{"0":{"graph":{"mode":"multiBarChart","height":300,"optionOpen":false,"setting":{"multiBarChart":{"rotate":{"degree":"-45"},"xLabelStatus":"default"}},"commonSetting":{},"keys":[{"name":"cid","index":0,"aggr":"sum"}],"groups":[],"values":[{"name":"count","index":1,"aggr":"sum"}]},"helium":{}}},"enabled":true,"editorSetting":{"language":"sql","editOnDblClick":false,"completionKey":"TAB","completionSupport":true},"fontSize":9,"editorHide":false,"title":true},"settings":{"params":{},"forms":{}},"results":{"code":"SUCCESS","msg":[{"type":"TABLE","data":"cid\tcount\n12\t311\n1\t1032\n13\t6135\n6\t21639\n16\t6602\n3\t3120\n5\t18077\n19\t114\n15\t31\n17\t5323\n9\t216\n4\t1179\n8\t73\n7\t2894\n10\t2708\n11\t3547\n14\t84\n2\t129\n0\t13834\n18\t752\n"}]},"runtimeInfos":{"jobUrl":{"propertyName":"jobUrl","label":"SPARK JOB","tooltip":"View in Spark web UI","group":"spark","values":["http://mapr-resman:8088/proxy/application_1540577802860_0022//jobs","http://mapr-resman:8088/proxy/application_1540577802860_0022//jobs","http://mapr-resman:8088/proxy/application_1540577802860_0022//jobs","http://mapr-resman:8088/proxy/application_1540577802860_0022//jobs","http://mapr-resman:8088/proxy/application_1540577802860_0022//jobs"],"interpreterSettingId":"spark"}},"apps":[],"jobName":"paragraph_1540326162169_-1941614151","id":"20180702-164649_1043869606","dateCreated":"2018-10-23T20:22:42+0000","dateStarted":"2018-10-29T20:46:40+0000","dateFinished":"2018-10-29T20:46:41+0000","status":"FINISHED","progressUpdateIntervalMs":500,"$$hashKey":"object:23090"},{"title":"What is the trip count by hour?","text":"%sql SELECT hour(uber.dt) as hr,count(cid) as ct FROM uber group By hour(uber.dt)","user":"mapr","dateUpdated":"2018-10-30T16:14:16+0000","config":{"colWidth":12,"editorMode":"ace/mode/sql","results":{"0":{"graph":{"mode":"multiBarChart","height":300,"optionOpen":false,"setting":{"multiBarChart":{"rotate":{"degree":"-45"},"xLabelStatus":"default"}},"commonSetting":{},"keys":[{"name":"hr","index":0,"aggr":"sum"}],"groups":[],"values":[{"name":"ct","index":1,"aggr":"sum"}]},"helium":{}}},"enabled":true,"editorSetting":{"language":"sql","editOnDblClick":false,"completionKey":"TAB","completionSupport":true},"fontSize":9,"editorHide":false,"title":true},"settings":{"params":{},"forms":{}},"results":{"code":"SUCCESS","msg":[{"type":"TABLE","data":"hr\tct\n12\t1085\n22\t2247\n1\t553\n13\t1398\n16\t2122\n6\t928\n3\t318\n20\t1923\n5\t604\n19\t2120\n15\t1885\n9\t1153\n17\t2242\n4\t412\n8\t1337\n23\t1794\n7\t1307\n10\t1109\n21\t2035\n11\t1079\n14\t1585\n2\t289\n0\t1479\n18\t2196\n"}]},"runtimeInfos":{"jobUrl":{"propertyName":"jobUrl","label":"SPARK JOB","tooltip":"View in Spark web UI","group":"spark","values":["http://mapr-resman:8088/proxy/application_1540577802860_0022//jobs","http://mapr-resman:8088/proxy/application_1540577802860_0022//jobs","http://mapr-resman:8088/proxy/application_1540577802860_0022//jobs","http://mapr-resman:8088/proxy/application_1540577802860_0022//jobs","http://mapr-resman:8088/proxy/application_1540577802860_0022//jobs"],"interpreterSettingId":"spark"}},"apps":[],"jobName":"paragraph_1540326162170_1013838747","id":"20180702-165646_164052550","dateCreated":"2018-10-23T20:22:42+0000","dateStarted":"2018-10-29T20:45:31+0000","dateFinished":"2018-10-29T20:45:32+0000","status":"FINISHED","progressUpdateIntervalMs":500,"$$hashKey":"object:23091"},{"title":"What is the trip count by day and cluster?","text":"%sql SELECT day(uber.dt) as day, cid, count(cid) as ct FROM uber group By day(uber.dt), cid\n","user":"mapr","dateUpdated":"2018-10-30T16:14:17+0000","config":{"colWidth":12,"editorMode":"ace/mode/sql","results":{"0":{"graph":{"mode":"multiBarChart","height":300,"optionOpen":false,"setting":{"multiBarChart":{"rotate":{"degree":"-45"},"xLabelStatus":"default"}},"commonSetting":{},"keys":[{"name":"day","index":0,"aggr":"sum"}],"groups":[{"name":"cid","index":1,"aggr":"sum"}],"values":[{"name":"ct","index":2,"aggr":"sum"}]},"helium":{}}},"enabled":true,"editorSetting":{"language":"sql","editOnDblClick":false,"completionKey":"TAB","completionSupport":true},"fontSize":9,"editorHide":false,"title":true},"settings":{"params":{},"forms":{}},"results":{"code":"SUCCESS","msg":[{"type":"TABLE","data":"day\tcid\tct\n3\t15\t4\n1\t0\t5258\n4\t10\t463\n3\t1\t312\n2\t2\t57\n3\t13\t1747\n2\t19\t45\n3\t18\t288\n1\t7\t833\n2\t3\t828\n4\t7\t298\n1\t2\t36\n4\t0\t1464\n1\t9\t96\n4\t11\t573\n1\t1\t275\n4\t9\t29\n1\t3\t1040\n2\t17\t2032\n2\t14\t30\n3\t10\t1122\n3\t5\t4328\n1\t11\t1220\n2\t5\t5264\n1\t4\t346\n2\t9\t62\n4\t17\t544\n4\t13\t691\n2\t15\t17\n3\t3\t1131\n4\t15\t1\n1\t8\t20\n3\t17\t1459\n1\t16\t2452\n1\t19\t42\n3\t19\t22\n4\t3\t567\n2\t1\t411\n2\t18\t181\n2\t4\t441\n3\t11\t913\n4\t6\t2521\n3\t14\t8\n1\t18\t222\n3\t6\t5544\n1\t14\t43\n3\t9\t50\n2\t0\t4785\n1\t17\t1604\n4\t19\t11\n2\t11\t1188\n2\t12\t102\n2\t10\t621\n1\t12\t115\n3\t2\t35\n4\t14\t14\n1\t5\t7855\n1\t15\t9\n3\t12\t81\n3\t8\t18\n1\t13\t1885\n3\t4\t341\n4\t2\t11\n4\t18\t150\n4\t4\t137\n2\t8\t35\n3\t16\t1526\n3\t0\t3363\n1\t6\t8262\n1\t10\t739\n4\t1\t118\n3\t7\t854\n2\t7\t1078\n4\t16\t1188\n4\t8\t1\n4\t5\t2498\n2\t13\t2256\n2\t16\t2233\n4\t12\t45\n2\t6\t7012\n"}]},"runtimeInfos":{"jobUrl":{"propertyName":"jobUrl","label":"SPARK JOB","tooltip":"View in Spark web UI","group":"spark","values":["http://mapr-resman:8088/proxy/application_1540577802860_0022//jobs","http://mapr-resman:8088/proxy/application_1540577802860_0022//jobs","http://mapr-resman:8088/proxy/application_1540577802860_0022//jobs","http://mapr-resman:8088/proxy/application_1540577802860_0022//jobs","http://mapr-resman:8088/proxy/application_1540577802860_0022//jobs"],"interpreterSettingId":"spark"}},"apps":[],"jobName":"paragraph_1540326162171_-953939357","id":"20180703-133749_833187486","dateCreated":"2018-10-23T20:22:42+0000","dateStarted":"2018-10-29T20:46:49+0000","dateFinished":"2018-10-29T20:46:50+0000","status":"FINISHED","progressUpdateIntervalMs":500,"$$hashKey":"object:23092"},{"title":"What is the trip count by base and cluster?","text":"%sql SELECT base, cid, count(cid) as ct FROM uber group By base, cid","user":"mapr","dateUpdated":"2018-10-30T16:14:17+0000","config":{"colWidth":12,"editorMode":"ace/mode/sql","results":{"0":{"graph":{"mode":"multiBarChart","height":300,"optionOpen":false,"setting":{"multiBarChart":{"rotate":{"degree":"-45"},"xLabelStatus":"default"}},"commonSetting":{},"keys":[{"name":"cid","index":1,"aggr":"sum"}],"groups":[{"name":"base","index":0,"aggr":"sum"}],"values":[{"name":"ct","index":2,"aggr":"sum"}]},"helium":{}}},"enabled":true,"editorSetting":{"language":"sql","editOnDblClick":false,"completionKey":"TAB","completionSupport":true},"fontSize":9,"editorHide":false,"title":true},"settings":{"params":{},"forms":{}},"results":{"code":"SUCCESS","msg":[{"type":"TABLE","data":"base\tcid\tct\nB02682\t7\t703\nB02617\t5\t9628\nB02598\t6\t6946\nB02764\t6\t291\nB02598\t12\t106\nB02682\t18\t182\nB02682\t2\t29\nB02764\t0\t190\nB02617\t2\t41\nB02512\t10\t125\nB02682\t1\t296\nB02764\t1\t26\nB02764\t4\t14\nB02512\t0\t690\nB02598\t8\t14\nB02512\t6\t1053\nB02598\t11\t1095\nB02764\t12\t14\nB02617\t13\t3078\nB02598\t18\t262\nB02512\t3\t156\nB02682\t4\t313\nB02764\t17\t93\nB02682\t19\t33\nB02682\t15\t6\nB02617\t7\t1475\nB02764\t16\t73\nB02512\t12\t21\nB02512\t2\t12\nB02617\t16\t3425\nB02617\t8\t8\nB02512\t1\t40\nB02598\t17\t1596\nB02598\t10\t880\nB02682\t10\t790\nB02512\t9\t23\nB02764\t7\t46\nB02617\t14\t33\nB02617\t10\t1335\nB02598\t16\t2155\nB02512\t8\t34\nB02617\t15\t9\nB02598\t5\t6284\nB02617\t6\t10861\nB02512\t5\t1015\nB02682\t6\t5554\nB02682\t14\t27\nB02598\t7\t897\nB02764\t15\t1\nB02764\t3\t57\nB02617\t1\t495\nB02598\t9\t69\nB02764\t10\t33\nB02617\t0\t6944\nB02764\t5\t289\nB02512\t4\t24\nB02617\t9\t74\nB02617\t18\t340\nB02764\t11\t54\nB02682\t9\t64\nB02682\t0\t3548\nB02512\t13\t146\nB02764\t13\t84\nB02598\t14\t27\nB02512\t7\t52\nB02617\t19\t55\nB02682\t3\t778\nB02617\t11\t1803\nB02512\t16\t345\nB02682\t17\t1418\nB02512\t19\t18\nB02682\t11\t958\nB02512\t18\t103\nB02598\t15\t11\nB02682\t12\t67\nB02764\t18\t23\nB02617\t17\t2597\nB02598\t4\t422\nB02598\t3\t1037\nB02682\t5\t4819\nB02598\t2\t55\nB02617\t12\t150\nB02617\t4\t553\nB02764\t2\t3\nB02598\t0\t4495\nB02682\t16\t1813\nB02682\t13\t1494\nB02682\t8\t18\nB02512\t11\t142\nB02512\t17\t108\nB02764\t9\t18\nB02617\t3\t1745\nB02598\t19\t22\nB02598\t13\t2038\nB02512\t15\t6\nB02512\t14\t11\nB02598\t1\t297\n"}]},"runtimeInfos":{"jobUrl":{"propertyName":"jobUrl","label":"SPARK JOB","tooltip":"View in Spark web UI","group":"spark","values":["http://mapr-resman:8088/proxy/application_1540577802860_0022//jobs","http://mapr-resman:8088/proxy/application_1540577802860_0022//jobs","http://mapr-resman:8088/proxy/application_1540577802860_0022//jobs","http://mapr-resman:8088/proxy/application_1540577802860_0022//jobs","http://mapr-resman:8088/proxy/application_1540577802860_0022//jobs"],"interpreterSettingId":"spark"}},"apps":[],"jobName":"paragraph_1540326162171_-1352490814","id":"20180703-133902_1691437154","dateCreated":"2018-10-23T20:22:42+0000","dateStarted":"2018-10-29T20:46:57+0000","dateFinished":"2018-10-29T20:46:58+0000","status":"FINISHED","progressUpdateIntervalMs":500,"$$hashKey":"object:23093"},{"title":"Stop Writing to Memory ","text":"streamingquery.stop()\n","user":"mapr","dateUpdated":"2018-10-29T20:53:10+0000","config":{"colWidth":12,"editorMode":"ace/mode/scala","results":{},"enabled":true,"editorSetting":{"language":"scala","editOnDblClick":false,"completionKey":"TAB","completionSupport":true},"fontSize":9,"editorHide":false,"title":true},"settings":{"params":{},"forms":{}},"results":{"code":"SUCCESS","msg":[]},"apps":[],"jobName":"paragraph_1540326162172_-1190584538","id":"20180702-164818_524483900","dateCreated":"2018-10-23T20:22:42+0000","dateStarted":"2018-10-29T20:47:01+0000","dateFinished":"2018-10-29T20:47:02+0000","status":"FINISHED","progressUpdateIntervalMs":500,"$$hashKey":"object:23094"},{"title":"Write to MapR-DB","text":"import com.mapr.db.spark.impl._\nimport com.mapr.db.spark.streaming._\nimport com.mapr.db.spark.sql._\nimport com.mapr.db.spark.streaming.MapRDBSourceConfig\n\nvar tableName: String = \"/apps/ubertable\"\nval writedb = cdf.writeStream\n   .format(MapRDBSourceConfig.Format)\n   .option(MapRDBSourceConfig.TablePathOption, tableName)\n   .option(MapRDBSourceConfig.IdFieldPathOption, \"_id\")\n   .option(MapRDBSourceConfig.CreateTableOption, false)\n   .option(\"checkpointLocation\", \"/tmp/uberdb\")\n   .option(MapRDBSourceConfig.BulkModeOption, true)\n   .option(MapRDBSourceConfig.SampleSizeOption, 1000)\n\n\n   ","user":"mapr","dateUpdated":"2018-10-29T20:53:49+0000","config":{"colWidth":12,"editorMode":"ace/mode/scala","results":{},"enabled":true,"editorSetting":{"language":"scala","editOnDblClick":false,"completionKey":"TAB","completionSupport":true},"fontSize":9,"editorHide":false,"title":true},"settings":{"params":{},"forms":{}},"results":{"code":"SUCCESS","msg":[{"type":"TEXT","data":"import com.mapr.db.spark.impl._\nimport com.mapr.db.spark.streaming._\nimport com.mapr.db.spark.sql._\nimport com.mapr.db.spark.streaming.MapRDBSourceConfig\ntableName: String = /apps/ubertable\nwritedb: org.apache.spark.sql.streaming.DataStreamWriter[UberwId] = org.apache.spark.sql.streaming.DataStreamWriter@3a35f727\n"}]},"apps":[],"jobName":"paragraph_1540326162173_1026386447","id":"20180702-170446_1522571339","dateCreated":"2018-10-23T20:22:42+0000","status":"READY","errorMessage":"","progressUpdateIntervalMs":500,"$$hashKey":"object:23095"},{"text":"writedb.start()","user":"mapr","dateUpdated":"2018-10-26T17:09:15+0000","config":{"colWidth":12,"editorMode":"ace/mode/scala","results":{},"enabled":true,"editorSetting":{"language":"scala","editOnDblClick":false,"completionKey":"TAB","completionSupport":true},"fontSize":9,"editorHide":false},"settings":{"params":{},"forms":{}},"results":{"code":"SUCCESS","msg":[{"type":"TEXT","data":"res26: org.apache.spark.sql.streaming.StreamingQuery = org.apache.spark.sql.execution.streaming.StreamingQueryWrapper@5f56e9a6\n"}]},"apps":[],"jobName":"paragraph_1540326162174_490249752","id":"20180709-161134_1518899157","dateCreated":"2018-10-23T20:22:42+0000","status":"READY","errorMessage":"","progressUpdateIntervalMs":500,"$$hashKey":"object:23096"},{"text":"writedb.stop()","user":"mapr","dateUpdated":"2018-10-26T17:09:16+0000","config":{"colWidth":12,"editorMode":"ace/mode/scala","results":{},"enabled":true,"editorSetting":{"language":"scala","editOnDblClick":false,"completionKey":"TAB","completionSupport":true},"fontSize":9,"editorHide":false},"settings":{"params":{},"forms":{}},"results":{"code":"SUCCESS","msg":[]},"apps":[],"jobName":"paragraph_1540326162175_1274487750","id":"20180702-171205_691156739","dateCreated":"2018-10-23T20:22:42+0000","status":"READY","errorMessage":"","progressUpdateIntervalMs":500,"$$hashKey":"object:23097"},{"title":"Write to a Kafka Topic","text":"// publish to a kafka topic\n val writek = cdf.selectExpr(\"CAST(base AS STRING) AS key\", \"CAST(lat AS STRING) AS value\").writeStream.format(\"kafka\")\n             .option(\"kafka.bootstrap.servers\",\"localhost:9092\").option(\"topic\", \"/apps/uberstream:uberp\")\n             .option(\"checkpointLocation\", \"/tmp/nsparkcheckpoint/\").queryName(\"kafka2\").outputMode(\"update\").start()","user":"mapr","dateUpdated":"2018-10-29T20:54:05+0000","config":{"editorSetting":{"language":"scala","editOnDblClick":false,"completionKey":"TAB","completionSupport":true},"colWidth":12,"editorMode":"ace/mode/scala","editorHide":false,"results":{},"enabled":true,"fontSize":9,"title":true},"settings":{"params":{},"forms":{}},"results":{"code":"SUCCESS","msg":[]},"apps":[],"jobName":"paragraph_1540326162175_815530424","id":"20180614-133413_1254318878","dateCreated":"2018-10-23T20:22:42+0000","status":"READY","errorMessage":"","progressUpdateIntervalMs":500,"$$hashKey":"object:23098"},{"text":"writek.stop()","user":"mapr","dateUpdated":"2018-10-26T17:09:16+0000","config":{"colWidth":12,"editorMode":"ace/mode/scala","results":{},"enabled":true,"editorSetting":{"language":"scala","editOnDblClick":false,"completionKey":"TAB","completionSupport":true},"fontSize":9,"editorHide":false},"settings":{"params":{},"forms":{}},"apps":[],"jobName":"paragraph_1540326162176_733543597","id":"20180710-124638_1511312471","dateCreated":"2018-10-23T20:22:42+0000","status":"READY","errorMessage":"","progressUpdateIntervalMs":500,"$$hashKey":"object:23099"},{"user":"mapr","dateUpdated":"2018-10-26T17:09:16+0000","config":{"tableHide":false,"editorSetting":{"language":"scala","editOnDblClick":false,"completionKey":"TAB","completionSupport":true},"colWidth":12,"editorMode":"ace/mode/scala","editorHide":false,"results":{},"enabled":true,"fontSize":9},"settings":{"params":{},"forms":{}},"apps":[],"jobName":"paragraph_1540326162177_1867939335","id":"20171003-225856_937234821","dateCreated":"2018-10-23T20:22:42+0000","status":"READY","errorMessage":"","progressUpdateIntervalMs":500,"$$hashKey":"object:23100"}],"name":"/cmcdonald/SparkUberStructuredStreaming","id":"2DSURKXCF","noteParams":{},"noteForms":{},"angularObjects":{"md:shared_process":[],"angular:shared_process":[],"sh:shared_process":[],"spark:shared_process":[]},"config":{"isZeppelinNotebookCronEnable":false,"looknfeel":"default","personalizedMode":"false"},"info":{}}